package_simple_dio/__init__.py
package_simple_dio/file1_name.py
package_simple_dio/file2_name.py
package_simple_dio-0.0.1.dist-info/METADATA
package_simple_dio-0.0.1.dist-info/WHEEL
package_simple_dio-0.0.1.dist-info/top_level.txt
package_simple_dio-0.0.1.dist-info/RECORD
